ws_comms/__init__.py
ws_comms/message.py
ws_comms/receiver.py
ws_comms/sender.py
ws_comms/client/__init__.py
ws_comms/client/client.py
ws_comms/client/client_route.py
ws_comms/server/__init__.py
ws_comms/server/server.py
ws_comms/server/server_route.py
wscomms-0.1.6.dist-info/LICENSE
wscomms-0.1.6.dist-info/METADATA
wscomms-0.1.6.dist-info/WHEEL
wscomms-0.1.6.dist-info/top_level.txt
wscomms-0.1.6.dist-info/RECORD
