Metadata-Version: 2.2
Name: wscomms
Version: 0.1.6
Summary: A WebSocket module enabling real-time communication between a server and multiple clients through a symmetric API, ensuring a consistent and easy-to-use interface on both ends.
Home-page: https://github.com/Florian-BARRE/WS_comms
Author: Florian BARRE
Author-email: florian.barre78@gmail.com
Classifier: Programming Language :: Python :: 3
Classifier: License :: OSI Approved :: GNU General Public License v3 (GPLv3)
Classifier: Operating System :: OS Independent
Requires-Python: >=3.10
License-File: LICENSE
Requires-Dist: aiohappyeyeballs>=2.4.4
Requires-Dist: aiohttp>=3.11.11
Requires-Dist: aiosignal>=1.3.2
Requires-Dist: attrs>=25.1.0
Requires-Dist: colorama>=0.4.6
Requires-Dist: contourpy>=1.3.1
Requires-Dist: cycler>=0.12.1
Requires-Dist: fonttools>=4.55.8
Requires-Dist: frozenlist>=1.5.0
Requires-Dist: idna>=3.10
Requires-Dist: kiwisolver>=1.4.8
Requires-Dist: loggerplusplus>=0.1.4
Requires-Dist: matplotlib>=3.10.0
Requires-Dist: multidict>=6.1.0
Requires-Dist: numpy>=2.2.2
Requires-Dist: packaging>=24.2
Requires-Dist: pillow>=11.1.0
Requires-Dist: propcache>=0.2.1
Requires-Dist: pyparsing>=3.2.1
Requires-Dist: python-dateutil>=2.9.0.post0
Requires-Dist: six>=1.17.0
Requires-Dist: yarl>=1.18.3
Dynamic: author
Dynamic: author-email
Dynamic: classifier
Dynamic: description
Dynamic: description-content-type
Dynamic: home-page
Dynamic: requires-dist
Dynamic: requires-python
Dynamic: summary
